<mediawiki xmlns="http://www.mediawiki.org/xml/export-0.3/" xmlns:xsi="http://www.w3.org/2001/XMLSchema-instance" xsi:schemaLocation="http://www.mediawiki.org/xml/export-0.3/ http://www.mediawiki.org/xml/export-0.3.xsd" version="0.3" xml:lang="en">
  <siteinfo>
    <sitename>sbgn.org</sitename>
    <base>http://www.sbgn.org/Main_Page</base>
    <generator>MediaWiki 1.12.0</generator>
    <case>first-letter</case>
      <namespaces>
      <namespace key="-2">Media</namespace>
      <namespace key="-1">Special</namespace>
      <namespace key="0" />
      <namespace key="1">Talk</namespace>
      <namespace key="2">User</namespace>
      <namespace key="3">User talk</namespace>
      <namespace key="4">sbgn.org</namespace>
      <namespace key="5">sbgn.org talk</namespace>
      <namespace key="6">Image</namespace>
      <namespace key="7">Image talk</namespace>
      <namespace key="8">MediaWiki</namespace>
      <namespace key="9">MediaWiki talk</namespace>
      <namespace key="10">Template</namespace>
      <namespace key="11">Template talk</namespace>
      <namespace key="12">Help</namespace>
      <namespace key="13">Help talk</namespace>
      <namespace key="14">Category</namespace>
      <namespace key="15">Category talk</namespace>
      <namespace key="274">Widget</namespace>
      <namespace key="275">Widget talk</namespace>
    </namespaces>
  </siteinfo>
  <page>
    <title>Community/SBGN4 Entity Relationships</title>
    <id>292</id>
    <revision>
      <id>1265</id>
      <timestamp>2008-10-16T07:41:53Z</timestamp>
      <contributor>
        <username>Lenov</username>
        <id>11</id>
      </contributor>
      <comment>New page: Discussion about the development of SBGN Entity Relationships.</comment>
      <text xml:space="preserve">Discussion about the development of SBGN Entity Relationships.</text>
    </revision>
  </page>
</mediawiki>
